feast_spark_offline_store/__init__.py
feast_spark_offline_store/spark.py
feast_spark_offline_store/spark_source.py
feast_spark_offline_store/spark_type_map.py
feast_spark_offline_store-0.0.5.dist-info/LICENSE
feast_spark_offline_store-0.0.5.dist-info/METADATA
feast_spark_offline_store-0.0.5.dist-info/WHEEL
feast_spark_offline_store-0.0.5.dist-info/top_level.txt
feast_spark_offline_store-0.0.5.dist-info/RECORD
