Metadata-Version: 2.1
Name: feast-spark-offline-store
Version: 0.0.5
Summary: Spark support for Feast offline store
Home-page: https://github.com/Adyen/feast-spark-offline-store
Author: Thijs Brits
License: MIT
Platform: UNKNOWN
Requires-Python: >=3.8.0
License-File: LICENSE
Requires-Dist: feast (>=0.15.0)
Requires-Dist: pyspark (>=3.0)
Requires-Dist: pyarrow (>=1.0.0)
Requires-Dist: numpy
Requires-Dist: pandas
Requires-Dist: pytz (>=2021.3)
Requires-Dist: pydantic (>=1.6)
Provides-Extra: dev
Requires-Dist: feast (>=0.15.0) ; extra == 'dev'
Requires-Dist: pyspark (>=3.0) ; extra == 'dev'
Requires-Dist: pyarrow (>=1.0.0) ; extra == 'dev'
Requires-Dist: numpy ; extra == 'dev'
Requires-Dist: pandas ; extra == 'dev'
Requires-Dist: pytz (>=2021.3) ; extra == 'dev'
Requires-Dist: pydantic (>=1.6) ; extra == 'dev'
Requires-Dist: wheel ; extra == 'dev'
Requires-Dist: black ; extra == 'dev'
Requires-Dist: flake8 ; extra == 'dev'
Requires-Dist: pytest (>=6.2.5) ; extra == 'dev'
Requires-Dist: google ; extra == 'dev'
